boostinator
